{"results":{"91b4d396cdd832534ee25936b828182d":{"original":{"label":"Add Recipe","locale":"en"},"translations":[]},"9791d7f5122b74abb96b2d7494a93e7e":{"original":{"label":"Disable Translation Mode","locale":"en"},"translations":[{"label":"Desactivar El Modo De Traducción"}]},"45b989aa3324f0d823b37472a8abec6f":{"original":{"label":"Powered By {brand}","locale":"en"},"translations":[]},"e43e5afd0f5bdbd47cf03a5dd84a1d5d":{"original":{"label":"Help Us Translate","locale":"en"},"translations":[{"label":"Ayúdanos a traducir"}]}},"sources":[]}